runllm/__init__.py
runllm/application.py
runllm/backend/__init__.py
runllm/backend/api_client.py
runllm/client.py
runllm/constants/__init__.py
runllm/constants/enums.py
runllm/constants/types.py
runllm/context.py
runllm/errors.py
runllm/exceptions.py
runllm/globals.py
runllm/primitives/__init__.py
runllm/primitives/custom.py
runllm/primitives/custom_primitive.py
runllm/primitives/embed.py
runllm/primitives/generate.py
runllm/primitives/methods.py
runllm/primitives/primitive.py
runllm/primitives/read.py
runllm/primitives/retrieve.py
runllm/primitives/spec.py
runllm/primitives/utils.py
runllm/primitives/write.py
runllm/resources/__init__.py
runllm/resources/parameters.py
runllm/resources/resources.py
runllm/task.py
runllm/utils/function_packaging.py
runllm/utils/utils.py
runllm-0.1.2.dist-info/METADATA
runllm-0.1.2.dist-info/WHEEL
runllm-0.1.2.dist-info/RECORD
