Metadata-Version: 2.1
Name: runllm
Version: 0.1.2
Summary: RunLLM Python SDK
Author: Aqueduct Developer
Author-email: hello@aqueducthq.com
Requires-Python: >=3.10,<4.0
Classifier: Programming Language :: Python :: 3
Classifier: Programming Language :: Python :: 3.10
Classifier: Programming Language :: Python :: 3.11
Requires-Dist: pydantic (==1.10.9)
Requires-Dist: requests (==2.31.0)
Requires-Dist: types-setuptools (>=68.1.0.0,<69.0.0.0)
